LICENSE
README.md
setup.py
Bili_UAS/__init__.py
Bili_UAS/bili_config.py
Bili_UAS/bili_live.py
Bili_UAS/bili_login.py
Bili_UAS/bili_user.py
Bili_UAS/bili_video.py
Bili_UAS/cli/__init__.py
Bili_UAS/cli/live_cli.py
Bili_UAS/cli/user_cli.py
Bili_UAS/cli/video_cli.py
Bili_UAS/scripts/__init__.py
Bili_UAS/scripts/config.py
Bili_UAS/scripts/log_in.py
Bili_UAS/scripts/video.py
Bili_UAS/utils/__init__.py
Bili_UAS/utils/config_utils.py
Bili_UAS/utils/live_utils.py
Bili_UAS/utils/search_utils.py
Bili_UAS/utils/train_utils.py
Bili_UAS/utils/user_utils.py
Bili_UAS/utils/utils.py
Bili_UAS/utils/video_utils.py
Bili_UAS/writer/__init__.py
Bili_UAS/writer/abnormal_monitor.py
Bili_UAS/writer/log_writer.py
bili_uas.egg-info/PKG-INFO
bili_uas.egg-info/SOURCES.txt
bili_uas.egg-info/dependency_links.txt
bili_uas.egg-info/entry_points.txt
bili_uas.egg-info/requires.txt
bili_uas.egg-info/top_level.txt
test/test.py