Metadata-Version: 2.1
Name: bili-uas
Version: 0.4.0
Summary: Assist up in personal, live, and video data analysis and prediction.
Home-page: https://github.com/jhzgjhzg/BiliBili-UP-Auxiliary-System
Author: jhzg
Author-email: jhzg02200059@163.com
License: AGPLv3
Keywords: BiliBili,auxiliary,analysis,live,video,word_cloud,monitor
Classifier: Development Status :: 3 - Alpha
Classifier: Intended Audience :: Developers
Classifier: Natural Language :: English
Classifier: Topic :: Software Development :: Build Tools
Classifier: Programming Language :: Python :: 3
Classifier: License :: OSI Approved :: GNU Lesser General Public License v3 (LGPLv3)
Requires-Python: >=3.9
License-File: LICENSE
